[
  {
    "query": "美联储宣布维持基准利率不变",
    "display_query": "美联储宣布维持基准利率不变"
  },
  { "query": "勇士vs森林狼", "display_query": "勇士vs森林狼" },
  { "query": "知乎旧物节", "display_query": "知乎旧物节" },
  { "query": "寻找穿越时光的旧物", "display_query": "寻找穿越时光的旧物" },
  {
    "query": "哪件旧物是你一直保留着的",
    "display_query": "哪件旧物是你一直保留着的"
  },
  { "query": "穿越时光的旧物", "display_query": "穿越时光的旧物" },
  {
    "query": "西安雷雨夜空现条状不明物",
    "display_query": "西安雷雨夜空现条状不明物"
  },
  {
    "query": "武大副教授被举报抄袭学生论文",
    "display_query": "武大副教授被举报抄袭学生论文"
  },
  {
    "query": "泡泡玛特股份被创始股东高位清仓",
    "display_query": "泡泡玛特股份被创始股东高位清仓"
  },
  {
    "query": "团队曝异瞳少年治沙为摆拍",
    "display_query": "团队曝异瞳少年治沙为摆拍"
  }
]
